financial_calculator/__init__.py
financial_calculator/calculator.py
financial_calculator-0.0.1.dist-info/LICENSE
financial_calculator-0.0.1.dist-info/METADATA
financial_calculator-0.0.1.dist-info/WHEEL
financial_calculator-0.0.1.dist-info/top_level.txt
financial_calculator-0.0.1.dist-info/RECORD
