Metadata-Version: 2.1
Name: financial-calculator
Version: 0.0.1
Summary: calculator to calculate EMI and SIP amount
Home-page: https://github.com/
Author: nioneer
Author-email: author@example.com
License: UNKNOWN
Project-URL: Bug Tracker, https://github.com/
Platform: UNKNOWN
Classifier: Programming Language :: Python :: 3
Classifier: License :: OSI Approved :: MIT License
Classifier: Operating System :: OS Independent
Requires-Python: >=3.6
